embeddings_plot/__init__.py
embeddings_plot/embeddings_plot.py
embeddings_plot-0.1.6.dist-info/LICENSE
embeddings_plot-0.1.6.dist-info/METADATA
embeddings_plot-0.1.6.dist-info/WHEEL
embeddings_plot-0.1.6.dist-info/entry_points.txt
embeddings_plot-0.1.6.dist-info/RECORD
