Metadata-Version: 2.1
Name: embeddings_plot
Version: 0.1.6
Summary: A command line utility to create plots of word embeddings
Home-page: https://github.com/robert-mcdermott/embeddings_plot
License: Apache-2.0
Keywords: word2vec,nlp,embeddings
Author: Robert McDermott
Author-email: robert.c.mcdermott@gmail.com
Requires-Python: >=3.9,<4.0
Classifier: License :: OSI Approved :: Apache Software License
Classifier: Programming Language :: Python :: 3
Classifier: Programming Language :: Python :: 3.9
Classifier: Programming Language :: Python :: 3.10
Classifier: Programming Language :: Python :: 3.11
Requires-Dist: argparse (>=1.4.0,<2.0.0)
Requires-Dist: gensim (>=4.3.2,<5.0.0)
Requires-Dist: numpy (>=1.26.2,<2.0.0)
Requires-Dist: pandas (>=2.1.3,<3.0.0)
Requires-Dist: plotly (>=5.18.0,<6.0.0)
Requires-Dist: scikit-learn (>=1.3.2,<2.0.0)
Requires-Dist: umap-learn (>=0.5.5,<0.6.0)
Project-URL: Repository, https://github.com/robert-mcdermott/embeddings_plot
